pydantic_marc/__init__.py
pydantic_marc/errors.py
pydantic_marc/fields.py
pydantic_marc/models.py
pydantic_marc/py.typed
pydantic_marc/rules.py
pydantic_marc/validators.py
pydantic_marc-0.1.0.dist-info/METADATA
pydantic_marc-0.1.0.dist-info/WHEEL
pydantic_marc-0.1.0.dist-info/RECORD
