Metadata-Version: 2.3
Name: pydantic-marc
Version: 0.1.0
Summary: A data validation tool for MARC records
License: MIT
Author: Charlotte Kostelic
Author-email: charlottekostelic@gmail.com
Requires-Python: >=3.9
Classifier: License :: OSI Approved :: MIT License
Classifier: Programming Language :: Python :: 3
Classifier: Programming Language :: Python :: 3.9
Classifier: Programming Language :: Python :: 3.10
Classifier: Programming Language :: Python :: 3.11
Classifier: Programming Language :: Python :: 3.12
Classifier: Programming Language :: Python :: 3.13
Requires-Dist: pydantic (>=2.10.6,<3.0.0)
